pyquadratic/__init__.py
pyquadratic/__main__.py
pyquadratic/pyquadratic.py
pyquadratic-1.0.4.dist-info/LICENSE
pyquadratic-1.0.4.dist-info/METADATA
pyquadratic-1.0.4.dist-info/WHEEL
pyquadratic-1.0.4.dist-info/entry_points.txt
pyquadratic-1.0.4.dist-info/top_level.txt
pyquadratic-1.0.4.dist-info/RECORD
