Metadata-Version: 2.1
Name: pyquadratic
Version: 1.0.4
Summary: A python package designed to facilitate the solving and manipulation of quadratic equations.
Author-email: Patrick Zhao <bz2099@nyu.edu>, Brad Yin <ry2050@nyu.edu>, Yucheng Xu <yx2354@nyu.edu>, Nicolas Izurieta <ni2050@nyu.edu>
License: GNU GENERAL PUBLIC LICENSE
Project-URL: Homepage, https://github.com/software-students-fall2023/3-python-package-exercise-kungheifatchoy
Keywords: algebra,math,equation,formula
Classifier: Programming Language :: Python :: 3
Classifier: Intended Audience :: Education
Classifier: License :: OSI Approved :: GNU General Public License v3 (GPLv3)
Classifier: Operating System :: OS Independent
Requires-Python: >=3.7
License-File: LICENSE
Provides-Extra: dev
Requires-Dist: pytest ; extra == 'dev'
